patched_slack_sdk/__init__.py
patched_slack_sdk/local_storage.py
patched_slack_sdk/patched_client.py
patched_slack_sdk-0.2.2.dist-info/LICENSE
patched_slack_sdk-0.2.2.dist-info/METADATA
patched_slack_sdk-0.2.2.dist-info/WHEEL
patched_slack_sdk-0.2.2.dist-info/RECORD
