Metadata-Version: 2.3
Name: patched-slack-sdk
Version: 0.2.2
Summary: A patched version of slack-sdk to allow the use of slack API without any access tokens creation. This patch uses existing credentials from the installed slack app.
Author: iYasha
Author-email: 33287747+iYasha@users.noreply.github.com
Requires-Python: >=3.8,<4.0
Classifier: Programming Language :: Python :: 3
Classifier: Programming Language :: Python :: 3.8
Classifier: Programming Language :: Python :: 3.9
Classifier: Programming Language :: Python :: 3.10
Classifier: Programming Language :: Python :: 3.11
Classifier: Programming Language :: Python :: 3.12
Classifier: Programming Language :: Python :: 3.13
Requires-Dist: cryptography (>=42.0.5,<43.0.0)
Requires-Dist: keyring (>=25.2.0,<26.0.0)
Requires-Dist: leveldb (>=0.201,<0.202)
Requires-Dist: slack-sdk (>=3.36.0,<4.0.0)
